twseia/__init__.py
twseia/__version__.py
twseia/constants.py
twseia/devices.py
twseia/packets.py
twseia/services.py
twseia/smart_application.py
twseia/utils.py
twseia-0.0.2.dist-info/LICENSE
twseia-0.0.2.dist-info/METADATA
twseia-0.0.2.dist-info/WHEEL
twseia-0.0.2.dist-info/top_level.txt
twseia-0.0.2.dist-info/RECORD
