Metadata-Version: 2.1
Name: twseia
Version: 0.0.2
Summary: A Python library for Taiwan Smart Energy Industry Association (TaiSEIA) protocol.
Home-page: https://twseia.readthedocs.io/
Author: Lee Shiueh
License: Apache 2.0
Platform: UNKNOWN
Requires-Dist: pyserial
